{"tokens":[{"tag":"DT","token":"Given"},{"tag":"NN","token":"two"},{"tag":"VBZ","token":"integers"},{"tag":"<code>","token":"<code>"},{"tag":"JJ","token":"dividend"},{"tag":"<code>","token":"<\/code>"},{"tag":"CC","token":"and"},{"tag":"<code>","token":"<code>"},{"tag":"NN","token":"divisor"},{"tag":"<code>","token":"<\/code>"},{"tag":",","token":","},{"tag":"DT","token":"divide"},{"tag":"NN","token":"two"},{"tag":"VBZ","token":"integers"},{"tag":"DT","token":"without"},{"tag":"NN","token":"using"},{"tag":"/NN","token":"multiplication"},{"tag":",","token":","},{"tag":"RB","token":"division"},{"tag":",","token":","},{"tag":"CC","token":"and"},{"tag":"DT","token":"mod"},{"tag":"NN","token":"operator"},{"tag":".","token":"."},{"tag":"DT","token":"Return"},{"tag":"NN","token":"the"},{"tag":"IN","token":"quotient"},{"tag":"DT","token":"after"},{"tag":"NN","token":"dividing"},{"tag":"<code>","token":"<code>"},{"tag":"VBN","token":"dividend"},{"tag":"<code>","token":"<\/code>"},{"tag":"IN","token":"by"},{"tag":"<code>","token":"<code>"},{"tag":"DT","token":"divisor"},{"tag":"<code>","token":"<\/code>"},{"tag":".","token":"."},{"tag":"DT","token":"The"},{"tag":"JJ","token":"integer"},{"tag":"NN","token":"division"},{"tag":"MD","token":"should"},{"tag":"VB","token":"truncate"},{"tag":"VBN","token":"toward"},{"tag":"IN","token":"zero"},{"tag":",","token":","},{"tag":"IN","token":"which"},{"tag":"DT","token":"means"},{"tag":"NN","token":"losing"},{"tag":"VBZ","token":"its"},{"tag":"JJ","token":"fractional"},{"tag":"NN","token":"part"},{"tag":".","token":"."},{"tag":"DT","token":"For"},{"tag":"NN","token":"example"},{"tag":",","token":","},{"tag":"<code>","token":"<code>"},{"tag":"DT","token":"truncate"},{"tag":"JJ","token":"("},{"tag":"NN","token":"8"},{"tag":".","token":"."},{"tag":"DT","token":"345"},{"tag":"JJ","token":")"},{"tag":"NN","token":"="},{"tag":"IN","token":"8"},{"tag":"<code>","token":"<\/code>"},{"tag":"CC","token":"and"},{"tag":"<code>","token":"<code>"},{"tag":"NN","token":"truncate"},{"tag":"IN","token":"("},{"tag":"DT","token":"-"},{"tag":"NN","token":"2"},{"tag":".","token":"."},{"tag":"DT","token":"7335"},{"tag":"NN","token":")"},{"tag":"IN","token":"="},{"tag":"DT","token":"-"},{"tag":"NN","token":"2"},{"tag":"<code>","token":"<\/code>"},{"tag":".","token":"."},{"tag":"DT","token":"Note"},{"tag":"JJ","token":":"},{"tag":"NN","token":"Assume"},{"tag":"IN","token":"we"},{"tag":"DT","token":"are"},{"tag":"NN","token":"dealing"},{"tag":"IN","token":"with"},{"tag":"DT","token":"an"},{"tag":"NN","token":"environment"},{"tag":"WDT","token":"that"},{"tag":"VBZ","token":"could"},{"tag":"DT","token":"only"},{"tag":"NN","token":"store"},{"tag":"/NN","token":"integers"},{"tag":"IN","token":"within"},{"tag":"DT","token":"the"},{"tag":"NN","token":"32"},{"tag":"MD","token":"-"},{"tag":"VB","token":"bit"},{"tag":"VBN","token":"signed"},{"tag":"IN","token":"integer"},{"tag":"DT","token":"range"},{"tag":"JJ","token":":"},{"tag":"<code>","token":"<code>"},{"tag":"NN","token":"["},{"tag":"IN","token":"−"},{"tag":"DT","token":"2"},{"tag":"NN","token":"31"},{"tag":",","token":","},{"tag":"DT","token":"2"},{"tag":"NN","token":"31"},{"tag":"IN","token":"−"},{"tag":"DT","token":"1"},{"tag":"NN","token":"]"},{"tag":"<code>","token":"<\/code>"},{"tag":".","token":"."},{"tag":"DT","token":"For"},{"tag":"NN","token":"this"},{"tag":"/NN","token":"problem"},{"tag":",","token":","},{"tag":"DT","token":"assume"},{"tag":"NN","token":"that"},{"tag":"IN","token":"your"},{"tag":"NN","token":"function"},{"tag":"NNS","token":"returns"},{"tag":"<code>","token":"<code>"},{"tag":"<code>","token":"2"},{"tag":"IN","token":"31"},{"tag":"DT","token":"−"},{"tag":"NN","token":"1"},{"tag":"<code>","token":"<\/code>"},{"tag":"IN","token":"when"},{"tag":"DT","token":"the"},{"tag":"NN","token":"division"},{"tag":"WP$","token":"result"},{"tag":"NN","token":"overflows"},{"tag":".","token":"."},{"tag":"DT","token":"Example"},{"tag":"NN","token":"1"},{"tag":":","token":":"},{"tag":"<code>","token":"<code>"},{"tag":"IN","token":"Input"},{"tag":":","token":":"},{"tag":"IN","token":"dividend"},{"tag":"DT","token":"="},{"tag":"NN","token":"10"},{"tag":",","token":","},{"tag":"RB","token":"divisor"},{"tag":"IN","token":"="},{"tag":"DT","token":"3"},{"tag":"NN","token":"Output"},{"tag":"IN","token":":"},{"tag":"DT","token":"3"},{"tag":"NN","token":"Explanation"},{"tag":":","token":":"},{"tag":"IN","token":"10"},{"tag":"DT","token":"/"},{"tag":"NN","token":"3"},{"tag":"IN","token":"="},{"tag":"DT","token":"truncate"},{"tag":"NN","token":"("},{"tag":"/NN","token":"3"},{"tag":".","token":"."},{"tag":"DT","token":"33333"},{"tag":".","token":"."},{"tag":"DT","token":"."},{"tag":"NN","token":")"},{"tag":"DT","token":"="},{"tag":"NN","token":"3"},{"tag":".","token":"."},{"tag":"<code>","token":"<\/code>"},{"tag":"DT","token":"Example"},{"tag":"NN","token":"2"},{"tag":":","token":":"},{"tag":"<code>","token":"<code>"},{"tag":"IN","token":"Input"},{"tag":":","token":":"},{"tag":"IN","token":"dividend"},{"tag":"DT","token":"="},{"tag":"NN","token":"7"},{"tag":",","token":","},{"tag":"DT","token":"divisor"},{"tag":"NN","token":"="},{"tag":"IN","token":"-"},{"tag":"DT","token":"3"},{"tag":"NN","token":"Output"},{"tag":":","token":":"},{"tag":"IN","token":"-"},{"tag":"DT","token":"2"},{"tag":"NN","token":"Explanation"},{"tag":":","token":":"},{"tag":"IN","token":"7"},{"tag":"DT","token":"/"},{"tag":"NN","token":"-"},{"tag":"IN","token":"3"},{"tag":"DT","token":"="},{"tag":"NN","token":"truncate"},{"tag":"IN","token":"("},{"tag":"DT","token":"-"},{"tag":"NN","token":"2"},{"tag":".","token":"."},{"tag":"DT","token":"33333"},{"tag":".","token":"."},{"tag":"DT","token":"."},{"tag":"NN","token":")"},{"tag":"DT","token":"="},{"tag":"JJ","token":"-"},{"tag":"NN","token":"2"},{"tag":".","token":"."},{"tag":"<code>","token":"<\/code>"},{"tag":"DT","token":"Example"},{"tag":"NN","token":"3"},{"tag":":","token":":"},{"tag":"<code>","token":"<code>"},{"tag":"IN","token":"Input"},{"tag":":","token":":"},{"tag":"IN","token":"dividend"},{"tag":"DT","token":"="},{"tag":"NN","token":"0"},{"tag":",","token":","},{"tag":"DT","token":"divisor"},{"tag":"NN","token":"="},{"tag":"IN","token":"1"},{"tag":"DT","token":"Output"},{"tag":"NN","token":":"},{"tag":".","token":"0"},{"tag":"<code>","token":"<\/code>"},{"tag":"NN","token":"Example"},{"tag":":","token":"4"},{"tag":"JJ","token":":"},{"tag":"<code>","token":"<code>"},{"tag":"NN","token":"Input"},{"tag":":","token":":"},{"tag":"IN","token":"dividend"},{"tag":"DT","token":"="},{"tag":"NN","token":"1"},{"tag":",","token":","},{"tag":"IN","token":"divisor"},{"tag":"DT","token":"="},{"tag":"NN","token":"1"},{"tag":"IN","token":"Output"},{"tag":"DT","token":":"},{"tag":"NN","token":"1"},{"tag":"<code>","token":"<\/code>"},{"tag":"VBZ","token":"Constraints"},{"tag":"DT","token":":"},{"tag":"<code>","token":"<code>"},{"tag":"NN","token":"-"},{"tag":"IN","token":"2"},{"tag":"WP","token":"31"},{"tag":"MD","token":""},{"tag":"VB","token":"="},{"tag":"VBN","token":"dividend"},{"tag":",","token":","},{"tag":"DT","token":"divisor"},{"tag":"NN","token":""},{"tag":"IN","token":"="},{"tag":"DT","token":"2"},{"tag":"NN","token":"31"},{"tag":"IN","token":"-"},{"tag":"DT","token":"1"},{"tag":"<code>","token":"<\/code>"},{"tag":"<code>","token":"<code>"},{"tag":"NN","token":"divisor"},{"tag":"IN","token":"!"},{"tag":"DT","token":"="},{"tag":"NN","token":"0"},{"tag":"<code>","token":"<\/code>"}],"type":"xml_converted"}